NOWNT/Database.py
NOWNT/Task.py
NOWNT/Test.py
NOWNT/User.py
NOWNT/__init__.py
NOWNT/web.py
project_abdallahziad-1.dist-info/LICENSE
project_abdallahziad-1.dist-info/METADATA
project_abdallahziad-1.dist-info/WHEEL
project_abdallahziad-1.dist-info/top_level.txt
project_abdallahziad-1.dist-info/RECORD
