Metadata-Version: 2.1
Name: project-abdallahziad
Version: 1
Summary: Testing
Home-page: UNKNOWN
Author: Abdallah Ziad
Author-email: boodyziad1@gmail.com
License: UNKNOWN
Platform: UNKNOWN
Classifier: Programming Language :: Python :: 3
Classifier: Operating System :: OS Independent
Requires-Python: >=3.6
License-File: LICENSE
